cookielab/__init__.py
cookielab/main.py
cookielab-0.0.1.dist-info/LICENSE
cookielab-0.0.1.dist-info/METADATA
cookielab-0.0.1.dist-info/WHEEL
cookielab-0.0.1.dist-info/top_level.txt
cookielab-0.0.1.dist-info/RECORD
