Metadata-Version: 2.1
Name: cookielab
Version: 0.0.1
Summary: An Util for python packaging.
Home-page: UNKNOWN
Author: df_coding
Author-email: df_coding@163.com
License: UNKNOWN
Keywords: spider,cookie
Platform: UNKNOWN
